xnodes/__init__.py
xnodes/x_core.py
xnodes/x_core_configuration.py
xnodes/x_event_handler.py
xnodes/x_node.py
xnodes/x_node_exception.py
xnodes-0.2.0.dist-info/LICENSE
xnodes-0.2.0.dist-info/METADATA
xnodes-0.2.0.dist-info/WHEEL
xnodes-0.2.0.dist-info/RECORD
