Metadata-Version: 2.1
Name: xnodes
Version: 0.2.0
Summary: XNodes is an application framework which provides an event mechanism for unrelated nodes by utilizing a global event bus
License: GPL-3.0
Author: newmra
Requires-Python: >=3.10,<4.0
Classifier: License :: OSI Approved :: GNU General Public License v3 (GPLv3)
Classifier: Programming Language :: Python :: 3
Classifier: Programming Language :: Python :: 3.10
Classifier: Programming Language :: Python :: 3.11
Classifier: Programming Language :: Python :: 3.12
